fim/__init__.py
fim/cli.py
file_handler-0.3.dist-info/METADATA
file_handler-0.3.dist-info/WHEEL
file_handler-0.3.dist-info/entry_points.txt
file_handler-0.3.dist-info/top_level.txt
file_handler-0.3.dist-info/RECORD
